sslpsk/__init__.py
sslpsk/_sslpsk.cp35-win32.pyd
sslpsk/sslpsk.py
sslpsk/test/__init__.py
sslpsk/test/__main__.py
sslpsk/test/test_sslpsk.py
sslpsk-1.0.0.data/data/sslpsk/libeay32MD.dll
sslpsk-1.0.0.data/data/sslpsk/ssleay32MD.dll
sslpsk-1.0.0.dist-info/DESCRIPTION.rst
sslpsk-1.0.0.dist-info/METADATA
sslpsk-1.0.0.dist-info/RECORD
sslpsk-1.0.0.dist-info/WHEEL
sslpsk-1.0.0.dist-info/metadata.json
sslpsk-1.0.0.dist-info/top_level.txt
